businessradar/__init__.py
businessradar/_base_client.py
businessradar/_client.py
businessradar/_compat.py
businessradar/_constants.py
businessradar/_exceptions.py
businessradar/_files.py
businessradar/_models.py
businessradar/_qs.py
businessradar/_resource.py
businessradar/_response.py
businessradar/_streaming.py
businessradar/_types.py
businessradar/_version.py
businessradar/pagination.py
businessradar/py.typed
businessradar/_utils/__init__.py
businessradar/_utils/_compat.py
businessradar/_utils/_datetime_parse.py
businessradar/_utils/_json.py
businessradar/_utils/_logs.py
businessradar/_utils/_proxy.py
businessradar/_utils/_reflection.py
businessradar/_utils/_resources_proxy.py
businessradar/_utils/_streams.py
businessradar/_utils/_sync.py
businessradar/_utils/_transform.py
businessradar/_utils/_typing.py
businessradar/_utils/_utils.py
businessradar/lib/.keep
businessradar/resources/__init__.py
businessradar/resources/companies.py
businessradar/resources/compliance.py
businessradar/resources/news/__init__.py
businessradar/resources/news/news.py
businessradar/resources/news/articles/__init__.py
businessradar/resources/news/articles/analytics.py
businessradar/resources/news/articles/articles.py
businessradar/resources/news/articles/export.py
businessradar/resources/portfolios/__init__.py
businessradar/resources/portfolios/companies.py
businessradar/resources/portfolios/portfolios.py
businessradar/types/__init__.py
businessradar/types/blank_enum.py
businessradar/types/company_create_missing_company_investigation_params.py
businessradar/types/company_create_missing_company_investigation_response.py
businessradar/types/company_create_params.py
businessradar/types/company_list_attribute_changes_params.py
businessradar/types/company_list_attribute_changes_response.py
businessradar/types/company_list_missing_company_investigations_params.py
businessradar/types/company_list_missing_company_investigations_response.py
businessradar/types/company_list_params.py
businessradar-1.11.0.dist-info/METADATA
businessradar-1.11.0.dist-info/WHEEL
businessradar-1.11.0.dist-info/licenses/LICENSE
businessradar-1.11.0.dist-info/RECORD
